{
  "content": [
    {
      "content": null,
      "created": "2022-01-08T11:08:17.854669Z",
      "format": null,
      "last_modified": "2022-01-08T11:07:22.551531Z",
      "mimetype": "application/javascript",
      "name": "CopyShader.js",
      "path": "simulator/js/shader/CopyShader.js",
      "size": 736,
      "type": "file",
      "writable": true
    },
    {
      "content": null,
      "created": "2022-01-08T11:08:17.854669Z",
      "format": null,
      "last_modified": "2022-01-08T11:07:22.551531Z",
      "mimetype": "application/javascript",
      "name": "LuminosityHighPassShader.js",
      "path": "simulator/js/shader/LuminosityHighPassShader.js",
      "size": 1468,
      "type": "file",
      "writable": true
    }
  ],
  "created": "2022-01-08T11:08:17.854669Z",
  "format": "json",
  "last_modified": "2022-01-08T11:08:17.854669Z",
  "mimetype": null,
  "name": "shader",
  "path": "simulator/js/shader",
  "size": null,
  "type": "directory",
  "writable": true
}